LICENSE
README.md
setup.py
autoconv/__init__.py
autoconv/autoconv_handler.py
autoconv/conversation.py
autoconv/state.py
autoconv/utils/__init__.py
autoconv/utils/persistence.py
autoconv/utils/telegram_data.py
autoconv/utils/timed_thread.py
telegram_autoconv.egg-info/PKG-INFO
telegram_autoconv.egg-info/SOURCES.txt
telegram_autoconv.egg-info/dependency_links.txt
telegram_autoconv.egg-info/requires.txt
telegram_autoconv.egg-info/top_level.txt