Metadata-Version: 2.1
Name: telegram-autoconv
Version: 0.0.69
Summary: A python module to auto build conversation for a Telegram bot
Home-page: https://github.com/mortafix/AutoConv-Telegram-Python
Author: Moris Doratiotto
Author-email: moris.doratiotto@gmail.com
License: UNKNOWN
Keywords: conversation,generator,telegram,bot
Platform: UNKNOWN
Classifier: Programming Language :: Python :: 3.9
Classifier: License :: OSI Approved :: MIT License
Classifier: Operating System :: OS Independent
Classifier: Development Status :: 3 - Alpha
Classifier: Intended Audience :: Developers
Requires-Python: >=3.9
